raga_llm_hub/__init__.py
raga_llm_hub/api_client_manager.py
raga_llm_hub/db_manager.py
raga_llm_hub/raga_llm_eval.py
raga_llm_hub/raga_llm_observer.py
raga_llm_hub/result_manager.py
raga_llm_hub/test_manager.py
raga_llm_hub/track_manager.py
raga_llm_hub/guardrails/__init__.py
raga_llm_hub/guardrails/anonymize.py
raga_llm_hub/guardrails/ban_competitors.py
raga_llm_hub/guardrails/ban_substrings.py
raga_llm_hub/guardrails/ban_topics.py
raga_llm_hub/guardrails/code.py
raga_llm_hub/guardrails/deanonymize.py
raga_llm_hub/guardrails/factual_consistency.py
raga_llm_hub/guardrails/gibberish.py
raga_llm_hub/guardrails/invisible_text.py
raga_llm_hub/guardrails/ir_metrics_test.py
raga_llm_hub/guardrails/json_verify.py
raga_llm_hub/guardrails/language.py
raga_llm_hub/guardrails/language_same.py
raga_llm_hub/guardrails/malicious_url.py
raga_llm_hub/guardrails/match_type.py
raga_llm_hub/guardrails/no_refusal.py
raga_llm_hub/guardrails/nsfw.py
raga_llm_hub/guardrails/politeness.py
raga_llm_hub/guardrails/profanity.py
raga_llm_hub/guardrails/reading_time.py
raga_llm_hub/guardrails/regex.py
raga_llm_hub/guardrails/secrets.py
raga_llm_hub/guardrails/sensitive.py
raga_llm_hub/guardrails/sentiment.py
raga_llm_hub/guardrails/token_limit.py
raga_llm_hub/guardrails/url_reachability.py
raga_llm_hub/guardrails/utils.py
raga_llm_hub/guardrails/valid_csv.py
raga_llm_hub/guardrails/valid_python.py
raga_llm_hub/guardrails/valid_sql.py
raga_llm_hub/guardrails/vault.py
raga_llm_hub/guardrails/anonymize_helpers/__init__.py
raga_llm_hub/guardrails/anonymize_helpers/analyzer.py
raga_llm_hub/guardrails/anonymize_helpers/exception.py
raga_llm_hub/guardrails/anonymize_helpers/faker.py
raga_llm_hub/guardrails/anonymize_helpers/ner_mapping.py
raga_llm_hub/guardrails/anonymize_helpers/regex_patterns.py
raga_llm_hub/guardrails/anonymize_helpers/transformers_helpers.py
raga_llm_hub/guardrails/anonymize_helpers/transformers_recognizer.py
raga_llm_hub-1.0.0.9.dist-info/LICENSE
raga_llm_hub-1.0.0.9.dist-info/METADATA
raga_llm_hub-1.0.0.9.dist-info/WHEEL
raga_llm_hub-1.0.0.9.dist-info/top_level.txt
raga_llm_hub-1.0.0.9.dist-info/RECORD
