Metadata-Version: 2.1
Name: raga-llm-hub
Version: 1.0.0.9
Summary: Package for LLM Evaluation
Author-email: Raga AI <rehan.asif@raga.ai>
License: Attribution-NonCommercial-NoDerivatives 4.0 International
Project-URL: Homepage, https://raga.ai
Project-URL: Documentation, https://docs.raga.ai/
Project-URL: Repository, https://github.com/raga-ai-hub/raga-llm-hub
Project-URL: Issues, https://github.com/raga-ai-hub/raga-llm-hub/issues
Keywords: ragaai,raga,llm,testing,llm-eval,llm-hub
Classifier: Development Status :: 5 - Production/Stable
Classifier: Intended Audience :: Developers
Classifier: Programming Language :: Python :: 3
Classifier: Programming Language :: Python :: 3.8
Classifier: Programming Language :: Python :: 3.9
Classifier: Programming Language :: Python :: 3.10
Classifier: Programming Language :: Python :: 3.11
Classifier: Operating System :: OS Independent
Requires-Python: >=3.8
License-File: LICENSE
Requires-Dist: prettytable ==3.9.0
Requires-Dist: toml ==0.10.2
Requires-Dist: datasets ==2.16.1
Requires-Dist: vaderSentiment ==3.3.2
Requires-Dist: llama-index ==0.9.48
Requires-Dist: nltk ==3.8.1
Requires-Dist: tensorflow
Requires-Dist: sentence-transformers ==2.4.0
Requires-Dist: textstat ==0.7.3
Requires-Dist: ir-measures ==0.3.3
Requires-Dist: optimum ==1.17.1
Requires-Dist: spacy ==3.7.4
Requires-Dist: presidio-analyzer ==2.2.353
Requires-Dist: presidio-anonymizer ==2.2.353
Requires-Dist: detect-secrets ==1.4.0
Requires-Dist: span-marker ==1.5.0
Requires-Dist: promptinject ==0.1.1.1
Requires-Dist: rapidfuzz ==3.6.1
Requires-Dist: langchain ==0.1.9
Requires-Dist: openai ==1.11.1
Requires-Dist: transformers ==4.38.1
Requires-Dist: Faker ==23.2.1
Requires-Dist: structlog ==24.1.0
Requires-Dist: json-repair ==0.9.0
Requires-Dist: fuzzysearch ==0.7.3
Requires-Dist: waitress ==3.0.0
Requires-Dist: sqlvalidator ==0.0.20
Provides-Extra: dev
Requires-Dist: black ; extra == 'dev'
Requires-Dist: flake8 ; extra == 'dev'
Requires-Dist: isort ; extra == 'dev'
Requires-Dist: mypy ; extra == 'dev'
Requires-Dist: pytest ; extra == 'dev'
Requires-Dist: pytest-cov ; extra == 'dev'
Requires-Dist: build ; extra == 'dev'
Provides-Extra: docs-dev
Requires-Dist: mkdocs ==1.5.3 ; extra == 'docs-dev'
Requires-Dist: mkdocs-autorefs ==0.5.0 ; extra == 'docs-dev'
Requires-Dist: mkdocs-material ==9.5.9 ; extra == 'docs-dev'
Requires-Dist: mkdocs-material-extensions ==1.3.1 ; extra == 'docs-dev'
Requires-Dist: mkdocstrings ==0.24.0 ; extra == 'docs-dev'
Requires-Dist: mkdocstrings-python ==1.8.0 ; extra == 'docs-dev'
Provides-Extra: onnxruntime
Provides-Extra: onnxruntime-gpu
Provides-Extra: ui
Requires-Dist: Flask ==3.0.2 ; extra == 'ui'
